behaviorci/__init__.py
behaviorci/cli.py
behaviorci/exceptions.py
behaviorci/bundle/__init__.py
behaviorci/bundle/dataset.py
behaviorci/bundle/loader.py
behaviorci/bundle/models.py
behaviorci/providers/__init__.py
behaviorci/providers/anthropic.py
behaviorci/providers/base.py
behaviorci/providers/mock.py
behaviorci/providers/openai.py
behaviorci/providers/registry.py
behaviorci/reporters/__init__.py
behaviorci/reporters/base.py
behaviorci/reporters/console.py
behaviorci/reporters/json_reporter.py
behaviorci/reporters/markdown.py
behaviorci/reporters/registry.py
behaviorci/runner/__init__.py
behaviorci/runner/engine.py
behaviorci/runner/evaluator.py
behaviorci/runner/thresholds.py
behaviorci-0.1.0.dist-info/METADATA
behaviorci-0.1.0.dist-info/WHEEL
behaviorci-0.1.0.dist-info/entry_points.txt
behaviorci-0.1.0.dist-info/licenses/LICENSE
behaviorci-0.1.0.dist-info/RECORD
