Metadata-Version: 2.4
Name: behaviorci
Version: 0.1.0
Summary: CI/CD for LLM behavior. Prompts don't ship until behavior passes tests.
Project-URL: Homepage, https://github.com/behaviorci/behaviorci
Project-URL: Documentation, https://github.com/behaviorci/behaviorci#readme
Project-URL: Repository, https://github.com/behaviorci/behaviorci
Project-URL: Issues, https://github.com/behaviorci/behaviorci/issues
Author: BehaviorCI Contributors
License-Expression: MIT
License-File: LICENSE
Keywords: behavior,cd,ci,evaluation,llm,prompts,testing
Classifier: Development Status :: 3 - Alpha
Classifier: Environment :: Console
Classifier: Intended Audience :: Developers
Classifier: License :: OSI Approved :: MIT License
Classifier: Operating System :: OS Independent
Classifier: Programming Language :: Python :: 3
Classifier: Programming Language :: Python :: 3.10
Classifier: Programming Language :: Python :: 3.11
Classifier: Programming Language :: Python :: 3.12
Classifier: Topic :: Scientific/Engineering :: Artificial Intelligence
Classifier: Topic :: Software Development :: Testing
Requires-Python: >=3.9
Requires-Dist: click<9,>=8.1
Requires-Dist: httpx<1,>=0.27
Requires-Dist: jinja2<4,>=3.1
Requires-Dist: jsonschema<5,>=4.21
Requires-Dist: pydantic<3,>=2.6
Requires-Dist: pyyaml<7,>=6.0.1
Requires-Dist: rich<14,>=13.7
Provides-Extra: dev
Requires-Dist: mypy<2,>=1.10; extra == 'dev'
Requires-Dist: pytest-asyncio<1,>=0.23; extra == 'dev'
Requires-Dist: pytest-cov<6,>=5.0; extra == 'dev'
Requires-Dist: pytest<9,>=8.0; extra == 'dev'
Requires-Dist: ruff<1,>=0.4; extra == 'dev'
Requires-Dist: types-pyyaml<7,>=6.0; extra == 'dev'
